py404/__init__.py
py404/main.py
py404-0.1.4.dist-info/METADATA
py404-0.1.4.dist-info/WHEEL
py404-0.1.4.dist-info/entry_points.txt
py404-0.1.4.dist-info/RECORD
